README.md
setup.py
pyrti/__init__.py
pyrti/rti.py
rti.egg-info/PKG-INFO
rti.egg-info/SOURCES.txt
rti.egg-info/dependency_links.txt
rti.egg-info/requires.txt
rti.egg-info/top_level.txt