Metadata-Version: 2.1
Name: rti
Version: 0.0.4
Summary: Pacote para integração do Request Tracker RT no PyPI
Home-page: https://github.com/infopontes/rti
Author: Marcelo Pontes Rodrigues
Author-email: infopontes@gmail.com
License: MIT License
Keywords: Pacote
Platform: UNKNOWN
